regression_model/VERSION
regression_model/__init__.py
regression_model/pipeline.py
regression_model/predict.py
regression_model/train_pipeline.py
regression_model/config_base/__init__.py
regression_model/config_base/core_test.py
regression_model/processing/__init__.py
regression_model/processing/data_manager.py
regression_model/trained_models/__init__.py
regression_model/trained_models/regression_model_output_v0.0.1.pkl
profit_prediction_model_xotik_105-0.0.1.dist-info/METADATA
profit_prediction_model_xotik_105-0.0.1.dist-info/WHEEL
profit_prediction_model_xotik_105-0.0.1.dist-info/top_level.txt
profit_prediction_model_xotik_105-0.0.1.dist-info/RECORD
